evn/.ninja_deps
evn/.ninja_log
evn/__init__.py
evn/__main__.py
evn/_prelude/__init__.py
evn/_prelude/basic_types.py
evn/_prelude/chrono.py
evn/_prelude/import_util.py
evn/_prelude/inspect.py
evn/_prelude/lazy_dispatch.py
evn/_prelude/lazy_import.py
evn/_prelude/make_decorator.py
evn/_prelude/run_info.py
evn/_prelude/structs.py
evn/_prelude/typehints.py
evn/_prelude/version.py
evn/cli/__init__.py
evn/cli/auto_click_decorator.py
evn/cli/basic_click_type_handlers.py
evn/cli/cli_command_resolver.py
evn/cli/cli_config.py
evn/cli/cli_logger.py
evn/cli/cli_metaclass.py
evn/cli/cli_registry.py
evn/cli/click_type_handler.py
evn/cli/click_util.py
evn/code/__init__.py
evn/code/gentest.py
evn/code/python_output.py
evn/config/__init__.py
evn/config/confload.py
evn/console/__init__.py
evn/console/shell.py
evn/console/table.py
evn/console/warnings.py
evn/decofunc/__init__.py
evn/decofunc/cache.py
evn/decofunc/deconfig.py
evn/decofunc/iterize.py
evn/decon/__init__.py
evn/decon/attr_access.py
evn/decon/bunch.py
evn/decon/item_wise.py
evn/decon/iterables.py
evn/decon/metadata.py
evn/dev/__init__.py
evn/dev/contexts.py
evn/dev/copy.py
evn/doc/__init__.py
evn/doc/docstring.py
evn/environment/__init__.py
evn/environment/apptainer.py
evn/format/.ninja_log
evn/format/__init__.py
evn/format/_common.hpp
evn/format/_detect_formatted_blocks.cpp
evn/format/_detect_formatted_blocks.pypy39-pp73-x86_64-linux-gnu.so
evn/format/_token_column_format.cpp
evn/format/_token_column_format.pypy39-pp73-x86_64-linux-gnu.so
evn/format/formatter.py
evn/ident/__init__.py
evn/ident/codes.py
evn/meta/__init__.py
evn/meta/codeinfo.py
evn/meta/kwargs_tunnel.py
evn/meta/kwcall.py
evn/testing/__init__.py
evn/testing/gen_tests.py
evn/testing/parametrized.py
evn/testing/pytest.py
evn/testing/quicktest.py
evn/testing/testapp.py
evn/tests/_prelude/broken_py_file.py
evn/tests/_prelude/test_basic_types.py
evn/tests/_prelude/test_chrono.py
evn-0.7.8.dist-info/METADATA
evn-0.7.8.dist-info/WHEEL
evn-0.7.8.dist-info/entry_points.txt
evn-0.7.8.dist-info/RECORD
evn-0.7.8.dist-info/licenses/LICENSE
