Metadata-Version: 2.2
Name: evn
Version: 0.7.8
Requires-Python: >=3.9
Requires-Dist: assertpy
Requires-Dist: click>=8.0
Requires-Dist: icecream
Requires-Dist: json5
Requires-Dist: ninja_import
Requires-Dist: more_itertools
Requires-Dist: multipledispatch
Requires-Dist: PrettyPrintTree
Requires-Dist: pyyaml
Requires-Dist: rapidfuzz
Requires-Dist: rich
Requires-Dist: ruff
Requires-Dist: tomli
Requires-Dist: typing_extensions
Requires-Dist: wrapt
Provides-Extra: dev
Requires-Dist: doit>=0.36.0; extra == "dev"
Requires-Dist: jsonschema; extra == "dev"
Requires-Dist: hypothesis; extra == "dev"
Requires-Dist: nox; extra == "dev"
Requires-Dist: pytest; extra == "dev"
Requires-Dist: pytest-xdist; extra == "dev"
Requires-Dist: pytest-benchmark; extra == "dev"
Requires-Dist: pytest-cov; extra == "dev"
Requires-Dist: pytest-sugar; extra == "dev"
Requires-Dist: tomlkit; extra == "dev"
